{
  "year": 2021,
  "indirmeler": [{
    "pardus": [{
        "Ay": "Jan",
        "PardusEtap": 0,
        "Pardus17Xfce": 0,
        "Pardus17Server": 0,
        "Pardus19Gnome": 0,
        "Pardus19Xfce": 0,
        "Pardus19Server": 0,
        "Pardus21Gnome": 0,
        "Pardus21Xfce": 0,
        "Pardus21Server": 0,
        "PardusToplam": 0
      },
      {
        "Ay": "Feb",
        "PardusEtap": 6919,
        "Pardus17Xfce": 543,
        "Pardus17Server": 450,
        "Pardus19Gnome": 6333,
        "Pardus19Xfce": 28853,
        "Pardus19Server": 1848,
        "Pardus21Gnome": 0,
        "Pardus21Xfce": 0,
        "Pardus21Server": 0,
        "PardusToplam": 38027
      },
      {
        "Ay": "Mar",
        "PardusEtap": 18792,
        "Pardus17Xfce": 934,
        "Pardus17Server": 473,
        "Pardus19Gnome": 47026,
        "Pardus19Xfce": 77765,
        "Pardus19Server": 2951,
        "Pardus19GnomeXfce": 5,
        "Pardus21Gnome": 0,
        "Pardus21Xfce": 0,
        "Pardus21Server": 0,
        "PardusToplam": 129149
      },
      {
        "Ay": "Apr",
        "PardusEtap": 6847,
        "Pardus17Xfce": 616,
        "Pardus17Server": 710,
        "Pardus19Gnome": 7512,
        "Pardus19Xfce": 35785,
        "Pardus19Server": 1171,
        "Pardus19GnomeXfce": 2,
        "Pardus21Gnome": 0,
        "Pardus21Xfce": 0,
        "Pardus21Server": 0,
        "PardusToplam": 45797
      },
      {
        "Ay": "May",
        "PardusEtap": 3076,
        "Pardus17Xfce": 400,
        "Pardus17Server": 649,
        "Pardus19Gnome": 8096,
        "Pardus19Xfce": 38447,
        "Pardus19Server": 1428,
        "Pardus21Gnome": 0,
        "Pardus21Xfce": 0,
        "Pardus21Server": 0,
        "PardusToplam": 49020
      },
      {
        "Ay": "Jun",
        "PardusEtap": 4960,
        "Pardus17Xfce": 914,
        "Pardus17Server": 380,
        "Pardus19Gnome": 3172,
        "Pardus19Xfce": 23838,
        "Pardus19Server": 703,
        "Pardus21Xfce": 1973,
        "Pardus21Gnome": 0,
        "Pardus21Server": 0,
        "PardusToplam": 30980
      },
      {
        "Ay": "Jul",
        "PardusEtap": 2057,
        "Pardus17Xfce": 330,
        "Pardus17Server": 11527,
        "Pardus19Gnome": 4044,
        "Pardus19Xfce": 22227,
        "Pardus19Server": 957,
        "Pardus21Gnome": 591,
        "Pardus21Xfce": 1904,
        "Pardus21Server": 0,
        "PardusToplam": 41580
      },
      {
        "Ay": "Aug",
        "PardusEtap": 3757,
        "Pardus17Xfce": 611,
        "Pardus17Server": 546,
        "Pardus19Gnome": 3383,
        "Pardus19Xfce": 13075,
        "Pardus19Server": 1087,
        "Pardus21Gnome": 58084,
        "Pardus21Xfce": 65981,
        "Pardus21Server": 15336,
        "PardusToplam": 158103
      },
      {
        "Ay": "Sep",
        "PardusEtap": 24679,
        "Pardus17Xfce": 818,
        "Pardus17Server": 676,
        "Pardus19Gnome": 1019,
        "Pardus19Xfce": 3249,
        "Pardus19Server": 1000,
        "Pardus21Gnome": 8520,
        "Pardus21Xfce": 39578,
        "Pardus21Server": 1548,
        "PardusToplam": 56408
      },
      {
        "Ay": "Oct",
        "PardusEtap": 131055,
        "Pardus17Xfce": 828,
        "Pardus17Server": 311,
        "Pardus19Gnome": 794,
        "Pardus19Xfce": 2479,
        "Pardus19Server": 551,
        "Pardus21Gnome": 8218,
        "Pardus21Xfce": 52018,
        "Pardus21Server": 892,
        "PardusToplam": 66091
      },
      {
        "Ay": "Nov",
        "PardusEtap": 11577,
        "Pardus17Xfce": 808,
        "Pardus17Server": 416,
        "Pardus19Gnome": 658,
        "Pardus19Xfce": 3389,
        "Pardus21Gnome": 5861,
        "Pardus21Xfce": 29791,
        "Pardus21Server": 1811,
        "Pardus19Server": 329,
        "PardusToplam": 43063
      },
      {
        "Ay": "Dec",
        "PardusEtap": 21646,
        "Pardus17Xfce": 1276,
        "Pardus17Server": 414,
        "Pardus19Gnome": 1083,
        "Pardus19Xfce": 3041,
        "Pardus21Gnome": 6769,
        "Pardus21Xfce": 35386,
        "Pardus21Server": 1059,
        "Pardus19Server": 386,
        "PardusToplam": 49414
      }
    ]
  }]
}
