{
  "year": 2025,
  "indirmeler": [
    {
      "pardus": [
        {
          "Ay": "Ocak",
          "PardusEtap": 1936,
          "DebianCount": 7339107,
          "Pardus19": 632,
          "Pardus21": 949,
          "Pardus23": 9684,
          "PardusToplam": 13201
        },
        {
          "Ay": "Şubat",
          "PardusEtap": 3525,
          "DebianCount": 6568558,
          "Pardus19": 916,
          "Pardus21": 1336,
          "Pardus23": 10600,
          "PardusToplam": 16377
        },
        {
          "Ay": "Mart",
          "PardusEtap": 2595,
          "DebianCount": 11906541,
          "Pardus19": 391,
          "Pardus21": 988,
          "Pardus23": 12549,
          "PardusToplam": 16523
        },
        {
          "Ay": "Nisan",
          "PardusEtap": 2016,
          "DebianCount": 19136383,
          "Pardus19": 262,
          "Pardus21": 770,
          "Pardus23": 16448,
          "PardusToplam": 19496
        },
        {
          "Ay": "Mayıs",
          "PardusEtap": 1874,
          "DebianCount": 19085056,
          "Pardus19": 321,
          "Pardus21": 866,
          "Pardus23": 12504,
          "PardusToplam": 15561
        },
        {
          "Ay": "Haziran",
          "PardusEtap": 1565,
          "DebianCount": 17804880,
          "Pardus19": 526,
          "Pardus21": 718,
          "Pardus23": 7119,
          "PardusToplam": 9928
        },
        {
          "Ay": "Temmuz",
          "PardusEtap": 1374,
          "DebianCount": 18488810,
          "Pardus19": 275,
          "Pardus21": 665,
          "Pardus23": 7504,
          "PardusToplam": 9818 
        },
        {
          "Ay": "Ağustos",
          "PardusEtap": 1787,
          "DebianCount": 17663922,
          "Pardus19": 440,
          "Pardus21": 667,
          "Pardus23": 8938,
          "PardusToplam": 11832
        },
        {
          "Ay": "Eylül",
          "PardusEtap": 7610,
          "DebianCount": 20205034,
          "Pardus19": 346,
          "Pardus21": 566,
          "Pardus23": 17896,
          "PardusToplam": 26418
        },
        {
          "Ay": "Ekim"
        },
        {
          "Ay": "Kasım"
        },
        {
          "Ay": "Aralık"
        }
      ]
    }
  ]
}
